gnani_grpc_client/__init__.py
gnani_grpc_client/cert.pem
gnani_grpc_client/client.py
gnani_grpc_client/stt_pb2.py
gnani_grpc_client/stt_pb2_grpc.py
gnani_grpc_client/audio/__init__.py
gnani_grpc_client/audio/english.amr
gnani_grpc_client/audio/english.wav
gnani_grpc_client/audio/gujarati.amr
gnani_grpc_client/audio/gujarati.wav
gnani_grpc_client/audio/hindi.amr
gnani_grpc_client/audio/hindi.wav
gnani_grpc_client/audio/kannada.amr
gnani_grpc_client/audio/kannada.wav
gnani_grpc_client/audio/marathi.amr
gnani_grpc_client/audio/marathi.wav
gnani_grpc_client/audio/tamil.amr
gnani_grpc_client/audio/tamil.wav
gnani_grpc_client/audio/telugu.amr
gnani_grpc_client/audio/telugu.wav
gnani_grpc_client/proto/__init__.py
gnani_grpc_client/proto/generate_pb.sh
gnani_grpc_client/proto/stt.proto
gnani_grpc_client/proto/stt_pb2.py
gnani_grpc_client/proto/stt_pb2_grpc.py
gnani_asr_grpc_api-0.0.1.dist-info/METADATA
gnani_asr_grpc_api-0.0.1.dist-info/WHEEL
gnani_asr_grpc_api-0.0.1.dist-info/top_level.txt
gnani_asr_grpc_api-0.0.1.dist-info/RECORD
