Metadata-Version: 2.1
Name: gnani-asr-grpc-api
Version: 0.0.1
Summary: gnani_asr_grpc_api
Home-page: UNKNOWN
Author: gnani.ai
Author-email: <api.service@gnani.ai>
License: UNKNOWN
Keywords: python,automatic_text_to_speech
Platform: UNKNOWN
Classifier: Development Status :: 3 - Alpha
Classifier: Intended Audience :: Education
Classifier: Programming Language :: Python :: 2
Classifier: Programming Language :: Python :: 3
Classifier: Operating System :: MacOS :: MacOS X
Classifier: Operating System :: Microsoft :: Windows
Requires-Dist: grpcio
Requires-Dist: grpcio-tools
